msicpe/__init__.py
msicpe/_version.py
msicpe/_tsatools/PSDEstimators.py
msicpe/_tsatools/__init__.py
msicpe/_tsatools/colored_noise.py
msicpe/_tsatools/estimatePDF.py
msicpe/_tsatools/generateAWN.py
msicpe/_tsatools/moments.py
msicpe/san/__init__.py
msicpe/san/correlate.py
msicpe/san/detect_fondamentale.py
msicpe/san/detect_pics.py
msicpe/san/trans_fourier.py
msicpe/ssl/EEG1_fe.npy
msicpe/ssl/EEG1_signal.npy
msicpe/ssl/FilTel.py
msicpe/ssl/PasseBas.py
msicpe/ssl/RecordModulation.py
msicpe/ssl/TransFourier.py
msicpe/ssl/TransFourier2.py
msicpe/ssl/TransFourierInv.py
msicpe/ssl/TransFourierPower.py
msicpe/ssl/__init__.py
msicpe/ssl/ansignal.py
msicpe/ssl/ansignal_old.py
msicpe/ssl/audioread.py
msicpe/ssl/avion_fe.npy
msicpe/ssl/avion_signal.npy
msicpe/ssl/carbr.py
msicpe/ssl/coque_fe.npy
msicpe/ssl/coque_signal.npy
msicpe/ssl/cs2_fe.npy
msicpe/ssl/cs2_signal.npy
msicpe/ssl/elephant_fe.npy
msicpe/ssl/elephant_signal.npy
msicpe/ssl/kurtosis.py
msicpe/ssl/vib_fe.npy
msicpe/ssl/vib_signal.npy
msicpe/tns/__init__.py
msicpe/tns/zplane.py
msicpe/tsa/__init__.py
msicpe/tsa/bin2data.py
msicpe/tsa/canal_test.py
msicpe/tsa/carbr.py
msicpe/tsa/data2bin.py
msicpe/tsa/ddpbr2.py
msicpe/tsa/ddpbr2f.py
msicpe/tsa/detsin.py
msicpe/tsa/fenetre.py
msicpe/tsa/genbrfill.py
msicpe/tsa/kurtosis.py
msicpe/tsa/load_signal.py
msicpe/tsa/reconstruct.py
msicpe/tsa/sptheo.py
msicpe/tsa/tracord.py
msicpe/tsa/transmit.py
msicpe/tsa/utils.py
msicpe/tsa/whitening.py
msicpe/tsa/data/DSP.MAT
msicpe/tsa/data/EEG.csv
msicpe/tsa/data/ENR.csv
msicpe/tsa/data/LPbutt.mat
msicpe/tsa/data/ProtestMonoBruitTronque.wav
msicpe/tsa/data/Sensor_data.csv
msicpe/tsa/data/sig.mat
msicpe/tsi/__init__.py
msicpe/tsi/figures.py
msicpe/tsi/morpho.py
msicpe/tsi/noise.py
msicpe/utils/__init__.py
msicpe/utils/export_dat.py
msicpe-1.0.21.dist-info/licenses/LICENSE
msicpe-1.0.21.dist-info/METADATA
msicpe-1.0.21.dist-info/WHEEL
msicpe-1.0.21.dist-info/top_level.txt
msicpe-1.0.21.dist-info/RECORD
