Metadata-Version: 2.4
Name: msicpe
Version: 1.0.21
Summary: Toolbox for Maths,Signal,Image Teaching @ CPE
Author-email: Marion Foare <marion.foare@cpe.fr>, Eric Van Reeth <eric.vanreeth@cpe.fr>, Arthur Gautheron <arthur.gautheron@cpe.fr>
Maintainer-email: Arthur Gautheron <arthur.gautheron@cpe.fr>, Marion Foare <marion.foare@cpe.fr>, Eric Van Reeth <eric.vanreeth@cpe.fr>
License: MIT License
Project-URL: Homepage, https://www.cpe.fr
Project-URL: Documentation, https://cpe.pages.in2p3.fr/msi/toolbox/
Project-URL: Moodle, https://e-campus.cpe.fr/course/view.php?id=539
Classifier: Programming Language :: Python :: 3
Classifier: License :: OSI Approved :: MIT License
Classifier: Operating System :: OS Independent
Requires-Python: >=3.8
License-File: LICENSE
Requires-Dist: numpy
Requires-Dist: scipy
Requires-Dist: plotly
Requires-Dist: dash
Requires-Dist: dash-bootstrap-components
Requires-Dist: sounddevice>=0.5
Requires-Dist: soundfile
Dynamic: license-file
